quantease_binance/__init__.py
quantease_binance/api.py
quantease_binance/config.py
quantease_binance/constants.py
quantease_binance/exceptions.py
quantease_binance/utils.py
quantease_binance-0.1.20.dist-info/LICENSE
quantease_binance-0.1.20.dist-info/METADATA
quantease_binance-0.1.20.dist-info/WHEEL
quantease_binance-0.1.20.dist-info/RECORD
