Metadata-Version: 2.3
Name: quantease-binance
Version: 0.1.20
Summary: This project provides a Python API for fetching historical data from the Binance exchange. It includes functionalities for retrieving Klines, trades, aggregate trades, book ticker data, funding rates, and metrics.
License: MIT
Author: river
Author-email: shinachuan@gmail.com
Requires-Python: >=3.10,<4.0
Classifier: License :: OSI Approved :: MIT License
Classifier: Programming Language :: Python :: 3
Classifier: Programming Language :: Python :: 3.10
Classifier: Programming Language :: Python :: 3.11
Classifier: Programming Language :: Python :: 3.12
Classifier: Programming Language :: Python :: 3.13
Requires-Dist: aiohttp (==3.10.6) ; sys_platform == "darwin"
Requires-Dist: aiohttp (==3.10.6) ; sys_platform == "linux"
Requires-Dist: aiohttp (==3.9.5) ; sys_platform == "win32"
Requires-Dist: asynciolimiter (==1.0.0)
Requires-Dist: httpx (==0.27.2)
Requires-Dist: pandas (==2.2.3)
Requires-Dist: pytest (==8.3.3)
Requires-Dist: python-dateutil (==2.9.0.post0)
Requires-Dist: tardis-dev (==2.0.0a13)
Requires-Dist: tenacity (>=9.0.0,<10.0.0)
Requires-Dist: tqdm (==4.66.5)
Requires-Dist: uvloop (>=0.21.0,<0.22.0) ; sys_platform != "win32"
Requires-Dist: winloop (>=0.1.6,<0.2.0) ; sys_platform == "win32"
